[{"id":"253","name":"Abarth Grande Punto S2000","path":"g.punto_s2000","filename":"g.punto_s2000","hash":"7ad65666fb09c35e3d6e7f2e361c7c9e","fallback":"5"},{"id":"75","name":"Alfa Romeo 33","path":"Alfa33","filename":"alfa33","hash":"6429bad8c33469f85847a2ae1d856cce","fallback":"0"},{"id":"96","name":"Alfa Romeo GTA 1967","path":"67_Alfa_Romeo_GTA","filename":"67_Alfa_Romeo_GTA","hash":"3f4abb598ef0654bed536313388c7b57","fallback":"2"},{"id":"247","name":"Alpine A110 Rally RGT","path":"Alpine_A110_2020","filename":"Alpine_A110_2020","hash":"432d3e75b4b0fcb7837752bf2c43b75b","fallback":"5"},{"id":"235","name":"Aston Martin Vantage RGT","path":"AstonMartin_Vantage_RGT","filename":"AstonMartin_Vantage_RGT","hash":"1333fd64063146e4de1c2f6a437c12b5","fallback":"5"},{"id":"165","name":"Audi 200 Quattro","path":"Audi_200_quattro","filename":"Audi_200_quattro","hash":"babb123cf1780086f314061d76aef337","fallback":"1"},{"id":"192","name":"Audi quattro A1 GrpB","path":"AUDI_QUATTRO_A1_GrpB","filename":"AUDI_QUATTRO_A1_GrpB","hash":"bc3db25f8784cd00283e7eeb8dbd84c0","fallback":"5"},{"id":"129","name":"Audi Quattro A2","path":"Audi_Quattro_A_2","filename":"Audi_Quattro_A_2","hash":"a42be6f69be829b41f81c9649469d77b","fallback":"1"},{"id":"236","name":"Audi quattro A2 GrpB","path":"AUDI_QUATTRO_A2_GrpB","filename":"AUDI_QUATTRO_A2_GrpB","hash":"a382ae68967833d7d7628c207f90bdfe","fallback":"5"},{"id":"204","name":"Audi Quattro Grp4","path":"AUDI_QUATTRO_Grp4","filename":"AUDI_QUATTRO_Grp4","hash":"7467ad8bc4f328a5ff4a2d58c3eca940","fallback":"5"},{"id":"130","name":"Audi Quattro S1","path":"AUDI_S1","filename":"audi_s1","hash":"a796b54dbbb454039b0a0ed74e9a0eeb","fallback":"1"},{"id":"131","name":"Audi Sport Quattro","path":"Audi_Sport_Quattro","filename":"Audi_Sport_Quattro","hash":"e65d2d093f025a7bc81c694894ee348f","fallback":"1"},{"id":"256","name":"BMW M1 GrpB","path":"BMW_M1","filename":"BMW_M1","hash":"46572c973f0c37e5d01ef9f3429bcf74","fallback":"5"},{"id":"97","name":"BMW M3 E30","path":"BMW_M3_E30","filename":"BMW_M3_E30","hash":"acf1e9d772b71af7a6645bfa9d26e041","fallback":"5"},{"id":"252","name":"BMW M3 E36 GrpA","path":"bmw_m3_e36","filename":"bmw_m3_e36","hash":"00eda97069097cc3f31d93bf0b290c14","fallback":"5"},{"id":"214","name":"Citroen AX Sport GrpA","path":"Citroen_AX","filename":"Citroen_AX","hash":"223fecdd7fa6185b25d706dd0bfcaedb","fallback":"5"},{"id":"132","name":"Citroen BX 4TC","path":"Citroen_BX_4TC","filename":"Citroen_BX_4TC","hash":"d9f38588836c372bc506fd0230a39a7c","fallback":"1"},{"id":"115","name":"Citroen C2 R2 Max","path":"C2_R2_Max","filename":"C2_R2_Max","hash":"496a5e70be0bc329b16fcba1082b50ea","fallback":"2"},{"id":"44","name":"Citroen C2 S1600","path":"CITROEN_C2_s1600","filename":"C2s1600","hash":"f2904360ce9ac39f62ff32675a9e0136","fallback":"4"},{"id":"212","name":"Citroen C3 R5","path":"C3_r5","filename":"C3_r5","hash":"d0b95fddd20cde5e0c04fc7dfe9f7a12","fallback":"5"},{"id":"191","name":"Citroen C3 WRC 2017","path":"Citroen_C3_WRC17","filename":"Citroen_C3_WRC17","hash":"53f367ffd57b8d7d6738981b44207cd4","fallback":"5"},{"id":"41","name":"Citroen C4 WRC","path":"C4","filename":"c4","hash":"a162a745bf80c1940d75227e9acf97ad","fallback":"3"},{"id":"257","name":"Citroen C4 WRC 2008","path":"C4_08","filename":"c4_08","hash":"a0a8e4b922b06f82f5f7f80012625f67","fallback":"5"},{"id":"143","name":"Citroen DS3 R1","path":"Citroen_DS3_R1","filename":"Citroen_DS3_R1","hash":"a23623b1e0320a1c068ec6bb7bf5960b","fallback":"5"},{"id":"81","name":"Citroen DS3 R3","path":"DS3_R3","filename":"DS3_R3","hash":"72b486e18f11d81d547453f24bb64aa4","fallback":"4"},{"id":"118","name":"Citroen DS3 R3 v2","path":"Citroen_DS3_R3","filename":"Citroen_DS3_R3","hash":"5f200d3dfb71aa004bbc9254279d76ab","fallback":"5"},{"id":"150","name":"Citroen DS3 R5","path":"DS3_R5","filename":"ds3_r5","hash":"343c49d23bd385f611c37bed501c7b35","fallback":"5"},{"id":"100","name":"Citroen DS3 S2000 1.6T","path":"DS3_RRC","filename":"ds3_rrc","hash":"e12e1758deec242e134875d754b531bc","fallback":"1"},{"id":"78","name":"Citroen DS3 WRC","path":"DS3_WRC","filename":"ds3_wrc","hash":"148a87069d8447ab1eeb4d321631df2d","fallback":"4"},{"id":"155","name":"Citroen DS3 WRC 2015","path":"DS3_WRC_2015","filename":"ds3_wrc_2015","hash":"148a87069d8447ab1eeb4d321631df2d","fallback":"1"},{"id":"30","name":"Citroen Saxo S1600","path":"SAXO_S1600","filename":"saxo","hash":"1a40c00ea94991090e49c3cf352e901f","fallback":"2"},{"id":"255","name":"Citroen Xsara Kit Car","path":"Citroen_Xsara_KitCar","filename":"Citroen_Xsara_KitCar","hash":"fb46c17fbf4941dcd97a81e879541435","fallback":"5"},{"id":"93","name":"Citroen Xsara KitCar","path":"Xsara_Kitcar","filename":"Xsara_Kitcar","hash":"b562e03eea4f9ded98a4f90434747205","fallback":"1"},{"id":"33","name":"Citroen Xsara WRC","path":"Xsara_05","filename":"xsara","hash":"e556e26be28a97069171c283ebec952d","fallback":"1"},{"id":"111","name":"Citroen Xsara WRC 2005","path":"Xsara_2005","filename":"xsara","hash":"339035d298d1d268374c0752c19f32c4","fallback":"1"},{"id":"18","name":"Citroen Xsara WRC 2006","path":"Xsara_2006","filename":"xsara","hash":"5046bbba622f14baf2d2768d9e15858a","fallback":"0"},{"id":"218","name":"Daewoo Lanos GrpA","path":"Daewoo_Lanos","filename":"Daewoo_Lanos","hash":"3b3ddb6754b2c5d29e7b92da989fe8a8","fallback":"1"},{"id":"196","name":"Datsun Violet 160J","path":"Datsun_Violet_160J","filename":"Datsun_Violet_160J","hash":"d073de274125fc6cd251e5d646a40d48","fallback":"1"},{"id":"205","name":"Datsun Violet GT Grp4","path":"Datsun_Violet_160J_LH","filename":"Datsun_Violet_160J_LH","hash":"7ac57a40995a7dca294c4d0c5be5cdf6","fallback":"1"},{"id":"213","name":"Fiat 124 Abarth Rally RGT","path":"124_Abarth_RGT","filename":"124_Abarth_RGT","hash":"2d8882b5b552f146803dadbe8d34108d","fallback":"5"},{"id":"125","name":"Fiat 125p","path":"fiat_125P","filename":"fiat_125P","hash":"e68f9363ea8d721fb8e1b396efea34e9","fallback":"2"},{"id":"258","name":"Fiat 131 Abarth Grp4","path":"131_Abarth_Gr4","filename":"131_Abarth_Gr4","hash":"3b695fafd85acf15a055f85f2768ae30","fallback":"5"},{"id":"82","name":"Fiat 500 R3","path":"Fiat_500_R3T","filename":"Fiat_500_R3T","hash":"2116733fabd810e786065051ac04e797","fallback":"4"},{"id":"127","name":"Fiat Abarth 131","path":"FIAT_ABARTH_131","filename":"FIAT_ABARTH_131","hash":"d044103526de902209a6fb5603b1dfb4","fallback":"2"},{"id":"119","name":"Fiat Abarth 500 R3T","path":"500_Abarth_R3T","filename":"500_Abarth_R3T","hash":"1756e3bf1a114b12389889fb8c195793","fallback":"4"},{"id":"60","name":"Fiat Grande Punto S2000","path":"grande_punto_s2000","filename":"g.punto_s2000","hash":"297b1fc99050195265ae41d045e56e1b","fallback":"0"},{"id":"121","name":"FIAT Panda KitCar","path":"Panda_KitCar","filename":"Panda_KitCar","hash":"28999a69994275265d750562eebe13ce","fallback":"2"},{"id":"84","name":"Fiat Punto R3","path":"Punto_R3D","filename":"Punto_R3D","hash":"e67ac0c5f4e7564f5c77ada5ecb676a4","fallback":"4"},{"id":"28","name":"Fiat Punto S1600","path":"PUNTO_1600_ATR2005","filename":"punto_1600","hash":"8ad3825650844a453ecab782407526b9","fallback":"2"},{"id":"215","name":"Fiat Seicento Sporting Kit GrpA","path":"Fiat_Seicento","filename":"Fiat_Seicento","hash":"30c2e65c8e94c36ebd9115b32c3f947c","fallback":"5"},{"id":"197","name":"Ford Capri RS 2600","path":"Ford_Capri_MK_1","filename":"fordcaprimk1","hash":"5430781be6af23839f9c899426cefba3","fallback":"1"},{"id":"126","name":"Ford Escort MK I","path":"Ford_Escort_mk1","filename":"Ford_Escort_mk1","hash":"13cdad7bc6a729049d33226473add74b","fallback":"2"},{"id":"241","name":"Ford Escort Mk II RS Grp4","path":"Escort_mk_2","filename":"Escort_mk_2","hash":"a139adf13c4cce78420025d370830cf1","fallback":"5"},{"id":"40","name":"Ford Escort RS Cosworth A8","path":"ESCORT_COSWORTH_GRA","filename":"Escort_Cosworth_GrA","hash":"c34610f8bdfd111c887962d9cb174ae9","fallback":"5"},{"id":"117","name":"Ford Escort WRC","path":"Escort_WRC","filename":"Escort_WRC","hash":"ee9859effeae7253100d5c240c4074d9","fallback":"5"},{"id":"237","name":"Ford Fiesta Mk VIII R2","path":"Fiesta_R2_2019","filename":"Fiesta_R2_2019","hash":"f400124b42a5e6807c2a21cce7fb4996","fallback":"5"},{"id":"228","name":"Ford Fiesta R2","path":"fiesta_r2","filename":"fiesta_r2","hash":"b1b73d7094f95614e69c839d2db9e1c0","fallback":"5"},{"id":"144","name":"Ford Fiesta R2T","path":"Fiesta_R2T","filename":"Fiesta_R2T","hash":"216462a142731a9164239a595a680dfb","fallback":"1"},{"id":"116","name":"Ford Fiesta R2_v1","path":"FIESTA_R2_original","filename":"fiesta_r2","hash":"08ebfecc65d04a901781fc07dce0c100","fallback":"2"},{"id":"151","name":"Ford Fiesta R5","path":"F_Fiesta_R5","filename":"F_Fiesta_R5","hash":"7600e67b1e70d583fa43a2a923ae70ae","fallback":"1"},{"id":"245","name":"Ford Fiesta Rally2","path":"fiesta_rally2","filename":"fiesta_rally2","hash":"2f766b67ff9ede9a8a287b234801cf11","fallback":"5"},{"id":"262","name":"Ford Fiesta Rally2 23","path":"fiesta_rally2_23","filename":"fiesta_rally2","hash":"902a456f8fea1c0b58e7267bfc16ba7b","fallback":"5"},{"id":"251","name":"Ford Fiesta Rally3","path":"Fiesta_rally3","filename":"Fiesta_rally3","hash":"46c0d4bc3d30c5dfb5a2a4151e9f700c","fallback":"5"},{"id":"244","name":"Ford Fiesta Rally4","path":"Fiesta_rally4","filename":"Fiesta_rally4","hash":"3d78805a5e1434e135abded21418d221","fallback":"5"},{"id":"37","name":"Ford Fiesta Rallye Concept","path":"Fiesta_RallyeConcept","filename":"fiesta_RallyeConcept","hash":"f340bb378e66f90b421b6d6be0549237","fallback":"2"},{"id":"101","name":"Ford Fiesta RRC","path":"Fiesta_RRC","filename":"fiesta_rrc","hash":"3febf05b095da4b20f014f955d109236","fallback":"1"},{"id":"156","name":"Ford Fiesta RS WRC 2012","path":"Fiesta_WRC_12","filename":"fiesta_wrc_12","hash":"c1957363f8646067cae195d481a68891","fallback":"1"},{"id":"157","name":"Ford Fiesta RS WRC 2014","path":"fiesta_wrc_14","filename":"fiesta_wrc_14","hash":"17ef26e742d7f28181735727d41fd9f1","fallback":"1"},{"id":"68","name":"Ford Fiesta S2000 v2010","path":"Fiesta_S2000","filename":"fiesta_s2000","hash":"c182017295e538936dde45fdad4fb2a4","fallback":"5"},{"id":"42","name":"Ford Fiesta ST N3","path":"FordFiestaST","filename":"fiestast","hash":"240003368045a22d87a3b7f459b4eee7","fallback":"4"},{"id":"79","name":"Ford Fiesta WRC 2011","path":"Fiesta_WRC","filename":"fiesta_wrc","hash":"4f1207f8a9275593aa37977e37840228","fallback":"4"},{"id":"187","name":"Ford Fiesta WRC 2017","path":"fiesta_wrc_17","filename":"fiesta_wrc_17","hash":"2ac66cfb3885667a527fb6f632a53a62","fallback":"1"},{"id":"226","name":"Ford Fiesta WRC 2019","path":"fiesta_wrc_19","filename":"fiesta_wrc_19","hash":"94b011bb511231d9e919c600720800d6","fallback":"5"},{"id":"16","name":"Ford Focus 2003 WRC","path":"Ford_Focus_2003","filename":"focus03","hash":"4dcec5ab06f680b24ea6b0fa8d73bd23","fallback":"3"},{"id":"17","name":"Ford Focus 2006 WRC","path":"FORD_FOCUS_2006","filename":"focus06","hash":"3d84c8efe019b5c6c50e5d5fef4322b3","fallback":"16"},{"id":"133","name":"Ford RS200","path":"FORD_RS200","filename":"ford_rs200","hash":"fe7e0bb2951dd8800991d7df3db8d1df","fallback":"1"},{"id":"98","name":"Ford Sierra RS","path":"Ford_Sierra_RS_Coswhorth_LH","filename":"Ford_Sierra_RS_Coswhorth_LH","hash":"37f924c7f5247b9e241caca28a6de8c1","fallback":"3"},{"id":"206","name":"FSO Polonez 2000","path":"Polonez2000","filename":"Polonez2000","hash":"9af4493a06b36ae6abd4f331fe8af666","fallback":"1"},{"id":"112","name":"Honda Civic EK4 (beta)","path":"Honda_Civic_EK4","filename":"Honda_Civic_EK4","hash":"5385b269266dc3173d6c7e2188875d03","fallback":"2"},{"id":"83","name":"Honda Civic R3","path":"HONDA_Civic_R3","filename":"Honda_Civic_R3","hash":"d84a96e0ec66c7c404321d8121f5d70d","fallback":"5"},{"id":"107","name":"Hyundai Accent WRC Evo3","path":"ACCENTevo3","filename":"accentevo3","hash":"118496f8afcf04a383eb709145cc4e68","fallback":"1"},{"id":"188","name":"Hyundai i20 Coupe WRC 2017","path":"i20_WRC_17","filename":"i20_wrc_17","hash":"e5fc460f70c693b991cae7e04220c052","fallback":"1"},{"id":"239","name":"Hyundai i20 Coupe WRC 2020","path":"i20_WRC_20","filename":"i20_wrc_20","hash":"3c8e06e76c536c8c7d78f62b63862a33","fallback":"5"},{"id":"261","name":"Hyundai i20 Coupe WRC 2021","path":"i20_WRC_21","filename":"i20_wrc_21","hash":"2b1434f162e44050b02dc7e0162bd2ec","fallback":"5"},{"id":"259","name":"Hyundai i20 N Rally2","path":"i20_rally2","filename":"i20_rally2","hash":"fd130364e2608ff2fc8e3dbf4ed8e95d","fallback":"5"},{"id":"152","name":"Hyundai i20 R5","path":"i20_R5","filename":"i20_R5","hash":"f8820ba4694350684a0c42773c661608","fallback":"1"},{"id":"158","name":"Hyundai i20 WRC 2014","path":"HYUNDAI_i20_WRC_2014","filename":"hyundai_i20_wrc","hash":"c0b2292940cac8efe4319036d5e87ac1","fallback":"1"},{"id":"159","name":"Hyundai i20 WRC 2016","path":"i20_WRC_16","filename":"i20_wrc_16","hash":"628432f5d16434f3e46f85bb75c4e765","fallback":"1"},{"id":"32","name":"Lada 112 S2000","path":"Lada_112","filename":"Lada_112","hash":"6a17fee2feb4f0bcfe9a4e3984ab91ae","fallback":"2"},{"id":"198","name":"Lada 1600R","path":"LADA_1600R","filename":"LADA_1600R","hash":"b5195b98a7fda2d57a7832bac1aff1f7","fallback":"1"},{"id":"128","name":"Lada 2105 VFTS","path":"Lada_2105_VFTS","filename":"Lada_VFTS","hash":"9a0755651d284621180824d5252494af","fallback":"1"},{"id":"39","name":"Lada 2107","path":"VAZ2107","filename":"VAZ2107","hash":"3a911812b030b9d28cd5ed8ec48187aa","fallback":"0"},{"id":"59","name":"Lada Kalina","path":"lada_kalina","filename":"lada_kalina","hash":"70fb49f04589e3118b7322637cc69dc9","fallback":"2"},{"id":"219","name":"LADA Kalina RC2 GrpA","path":"kalina_rc2","filename":"kalina_rc2","hash":"8d8461189b3c5f45ed4c893cfc8ac19e","fallback":"5"},{"id":"66","name":"Lada Samara","path":"lada_samara","filename":"lada_samara","hash":"3c2dc02830989b8e7afdbf532c528ef2","fallback":"59"},{"id":"71","name":"Lada VFTS","path":"Lada_VFTS","filename":"Lada_VFTS","hash":"dd97b9945e8e3199a942af7a704ee756","fallback":"39"},{"id":"134","name":"Lada VFTS NGP","path":"Lada_VFTS_NGP","filename":"Lada_VFTS_NGP","hash":"6205020ca14deb17218ce861f8aa1bb6","fallback":"1"},{"id":"135","name":"Lancia 037 Rally Evo II","path":"Lancia_037","filename":"Lancia_037","hash":"9c5bfaa81d847af572351cc521a335f8","fallback":"1"},{"id":"35","name":"Lancia Delta","path":"delta","filename":"delta","hash":"5649121bf6aa6c34a67aca7bde965d98","fallback":"0"},{"id":"166","name":"Lancia Delta HF 4WD","path":"delta_4wd","filename":"delta_4wd","hash":"eb6de64e3899269627696d22d33fbeec","fallback":"1"},{"id":"168","name":"Lancia Delta HF Integrale 16V","path":"delta_16v","filename":"delta_16v","hash":"ddfa8b7355aa769d82c4df982b2c2d58","fallback":"1"},{"id":"167","name":"Lancia Delta HF Integrale 8V","path":"delta_8v","filename":"delta_8v","hash":"e34c41a5ca219322bb4864813fa759c9","fallback":"1"},{"id":"136","name":"Lancia Delta S4","path":"Lancia_Delta_S4_SanRemo","filename":"Lancia_Delta_S4_SanRemo","hash":"40079e2690d441581eb46d6695552f47","fallback":"1"},{"id":"248","name":"Lancia Stratos HF Grp4","path":"Lancia_stratos","filename":"Lancia_Stratos","hash":"767da3f117626cd4e353c0a5f8c03b7f","fallback":"5"},{"id":"184","name":"Lotus Exige","path":"Lotus_Exige","filename":"Lotus_Exige","hash":"88f55d33e40f3c74c3fb7ea22bacee88","fallback":"5"},{"id":"169","name":"Mazda 323 BF 4WD Turbo","path":"MAZDA_323_BFMR","filename":"MAZDA_323_BFMR","hash":"5aa6201c94b2452a6dfe9b5861f3d2ce","fallback":"1"},{"id":"170","name":"Mazda 323 GTR","path":"Mazda_323_GT-R","filename":"Mazda_323_GT-R","hash":"41d26297782a7e605a9788b8c09239ab","fallback":"1"},{"id":"171","name":"Mazda 323 GTX","path":"Mazda_323_GT-X","filename":"Mazda_323_GT-X","hash":"7680755b64de92fe2b3f3d8c546c8580","fallback":"1"},{"id":"199","name":"Mercedes 500 SLC","path":"Mercedes_Benz_500SLC","filename":"Mercedes_Benz_500SLC","hash":"259136fed225b33a19bc2e55a2c81d49","fallback":"1"},{"id":"99","name":"Mercedes Benz 190E","path":"Mercedes_Benz_190E","filename":"Mercedes_Benz_190E","hash":"7c818eb2c4bf9eb5b2d6c4ca651815da","fallback":"3"},{"id":"122","name":"Mini Cooper 1275","path":"Mini_Cooper_1275","filename":"Mini_Cooper_S","hash":"42bcfb857641997862a0c3f72f9d318d","fallback":"2"},{"id":"102","name":"Mini JCW 1.6T S2000","path":"Mini_km_s2000","filename":"mini_km_s2000","hash":"158876e7212f15b801655583f23a82c3","fallback":"4"},{"id":"160","name":"Mini JCW WRC","path":"MINI_WRC01B","filename":"mini_wrc01b","hash":"e5033a605ee1553b8488408985231390","fallback":"5"},{"id":"85","name":"Mini WRC","path":"MINI_WRC","filename":"mini_wrc","hash":"768b2b84883a32fbe88df608f4ee3168","fallback":"4"},{"id":"172","name":"Mitsubishi Galant VR-4","path":"Galant_VR4","filename":"Galant_VR4","hash":"adca00abbebe2d433402fe591068cebb","fallback":"1"},{"id":"173","name":"Mitsubishi Lancer Evo II","path":"LANCER_EVO_II","filename":"LANCER_EVO_II","hash":"297693778c88da10422de7d3007c34bb","fallback":"1"},{"id":"22","name":"Mitsubishi Lancer EVO IX N","path":"evo_IX","filename":"evo_IX","hash":"60965d265ecddd7b91b47760840de374","fallback":"3"},{"id":"36","name":"Mitsubishi Lancer EVO VI A8","path":"LANCER_EVO_65","filename":"Lancer_Evo_65","hash":"e861ea76ad94655b32eb95434aeabd47","fallback":"3"},{"id":"20","name":"Mitsubishi Lancer EVO VII N","path":"LANCER_EVO_VII_GrN","filename":"Lancer_Evo_VII_GrN","hash":"27c5cfffda850ec111686b4ca579b9c6","fallback":"3"},{"id":"21","name":"Mitsubishi Lancer EVO VIII N","path":"LANCER_EVO_8_GrN","filename":"Lancer_Evo8_GrN","hash":"7b586bcad71aaaff541c5aaa64e39353","fallback":"20"},{"id":"62","name":"Mitsubishi Lancer EVO X GrN","path":"LANCER_EVO_X","filename":"lancer_evo_X","hash":"6c2d413e20b0bed908574ca8e4799870","fallback":"22"},{"id":"163","name":"Mitsubishi Lancer Evo X N v1.21","path":"LANCER_EVO_X_v1_21","filename":"lancer_evo_X","hash":"f16fe1d681711b579f3fd10beea35925","fallback":"1"},{"id":"174","name":"Mitsubishi Lancer RS Evo","path":"LANCER_EVO_I","filename":"LANCER_EVO_I","hash":"36b05c3d4b46940ec16ceca8eaf6c934","fallback":"1"},{"id":"54","name":"Mitsubishi Lancer WRC 2005","path":"LANCER_WRC05","filename":"Lancer_WRC05","hash":"40b9a0b7afd84db36fbb6bc40ad05103","fallback":"3"},{"id":"175","name":"Nissan 200SX RVS12","path":"Nissan_200SX","filename":"Nissan_200SX","hash":"88f2d730adec8f1fc157c94dcab97860","fallback":"1"},{"id":"220","name":"Nissan Sunny GTi (N14) GrpA","path":"Sunny_F2","filename":"Sunny_F2","hash":"bb18c791c2c8c9b85a91413128cf5d61","fallback":"1"},{"id":"176","name":"Nissan Sunny GTi-R","path":"Sunny_GTi-R","filename":"Sunny_GTi-R","hash":"ae2b0e658a3107760961495dfcf0ae6a","fallback":"1"},{"id":"145","name":"Opel Adam R2","path":"Opel_Adam_R2","filename":"Opel_Adam_R2","hash":"233ae8c8a0050570d718f8cb73fe98f4","fallback":"1"},{"id":"137","name":"Opel Ascona 400 Grp4","path":"Opel_Ascona_400","filename":"Opel_Ascona_400","hash":"6b9ba34a82b6351f2f93804a906fbf44","fallback":"5"},{"id":"77","name":"Opel Astra GSI","path":"AstraGSI","filename":"AstraGSI","hash":"ce7d4e9f5ac18a90eb938069f446f6ac","fallback":"0"},{"id":"181","name":"Opel Corsa S2000","path":"OPEL_CORSA_S2000","filename":"Opel_Corsa_s2000","hash":"48144b81e9ef8f3669b425f9aba052c0","fallback":"1"},{"id":"207","name":"Opel Kadett C GTE","path":"opel_kadett_GTE","filename":"opel_kadett_GTE","hash":"f06a7b2065f93b4ba180dc05d5786c73","fallback":"1"},{"id":"221","name":"Opel Kadett-E GSi 16V GrpA","path":"Opel_Kadett_gsi","filename":"opel_kadett_gsi","hash":"6e2fccf1c0c4db50d0898ffce7fd5dda","fallback":"1"},{"id":"138","name":"Opel Manta 400","path":"OPEL_MANTA_400","filename":"OPEL_MANTA_400","hash":"9666c4a758a677bb5ba3db1d45c4a1ba","fallback":"1"},{"id":"67","name":"Peugeot 106","path":"p106","filename":"p106","hash":"83d62fa42df4c10491f8832200dc8938","fallback":"4"},{"id":"250","name":"Peugeot 106 Rallye S20 GrpA","path":"Peugeot106_rally","filename":"Peugeot106_rally","hash":"31e30c96ca86785aa2395b7de08f2c6c","fallback":"4"},{"id":"76","name":"Peugeot 205 gti","path":"PEUGEOT_205_GTI","filename":"Peugeot_205_gti","hash":"fe1e5c681c5714214d7a8d19d2256ec2","fallback":"4"},{"id":"86","name":"Peugeot 205 Maxi","path":"PEUGEOT_205_Maxi","filename":"Peugeot_205_maxi","hash":"8f079e6790c1a5d2273fb4b86ecae3ca","fallback":"4"},{"id":"139","name":"Peugeot 205 T16","path":"PEUGEOT_205_T16_e1","filename":"PEUGEOT_205_T16_e1","hash":"533ac49a515607f8665b6888f29ad215","fallback":"4"},{"id":"140","name":"Peugeot 205 T16 Evo2","path":"PEUGEOT_205_T16_evo2","filename":"PEUGEOT_205_T16_evo2","hash":"1ef30bdeb0a6c54a57ca8dbdc3983d26","fallback":"1"},{"id":"57","name":"Peugeot 206 N3","path":"PEUGEOT_206_grN","filename":"Peugeot_206_grN","hash":"d5ed49f84d174410e1f787e6ad6f05ba","fallback":"4"},{"id":"25","name":"Peugeot 206 S1600","path":"PEUGEOT_206_s1600","filename":"Peugeot_206","hash":"19a74e1610ef5e917376af169e713676","fallback":"4"},{"id":"106","name":"Peugeot 206 WRC 2003","path":"PEUGEOT_206_2003","filename":"Peugeot_206_2003","hash":"9590df7a6d6f484997f0a4325dadbfdf","fallback":"4"},{"id":"80","name":"Peugeot 207 R3","path":"207_R3T","filename":"207_R3T","hash":"53a204bd6abdd4397bb0aedb88e98140","fallback":"46"},{"id":"120","name":"Peugeot 207 R3 v1","path":"Peugeot_207_R3","filename":"Peugeot_207_R3","hash":"9349d7244f88ee5acb167bc90935c4ed","fallback":"4"},{"id":"46","name":"Peugeot 207 S2000","path":"207_s2000","filename":"207_s2000","hash":"441d5115d94fc1c6f649a5ae23b09d94","fallback":"4"},{"id":"182","name":"Peugeot 207 S2000 EvoPlus","path":"207_s2000_2012","filename":"207_s2000_2012","hash":"04105a079279b12b117db426cfefef8c","fallback":"4"},{"id":"229","name":"Peugeot 208 R2_2","path":"PEUGEOT_208_R_2","filename":"PEUGEOT_208_R_2","hash":"2df639aae1a41fd650798a20a5c2624f","fallback":"5"},{"id":"249","name":"Peugeot 208 Rally4","path":"PEUGEOT_208_Rally4","filename":"PEUGEOT_208_Rally4","hash":"6bf9d2182d75479bcd8a1b0ee085302c","fallback":"4"},{"id":"153","name":"Peugeot 208 T16","path":"208_r5_2015","filename":"208_r5_2015","hash":"a7998b53fc9e80bb8538dd7f256dc7b6","fallback":"1"},{"id":"260","name":"Peugeot 208 T16 R5","path":"208_T16_R5_evo","filename":"208_T16_R5_evo","hash":"b4361827c09dff375b37cfc2403267f7","fallback":"4"},{"id":"146","name":"Peugeot 208 VTi R2","path":"Peugeot_208_R2","filename":"Peugeot_208_R2","hash":"9e426d184d62558bba5db0bdda8f7390","fallback":"1"},{"id":"65","name":"Peugeot 306 GrN","path":"PEUGEOT_306_grN","filename":"peugeot_306_grN","hash":"90ad6898f8b9793d26e26df56f4c5241","fallback":"0"},{"id":"48","name":"Peugeot 306 Maxi kitcar","path":"p306maxi","filename":"p306maxi","hash":"6405901d74b29164e5e6495b567d8a76","fallback":"4"},{"id":"19","name":"Peugeot 307 WRC 2005","path":"ATR_P307_WRC05","filename":"ATR_P307","hash":"54b8fe574d47a314b05ac12aa20fac2a","fallback":"3"},{"id":"70","name":"Peuteot 307 WRC","path":"Peugeot_307_wrc","filename":"Peugeot_307","hash":"777e96ec64d20d520b86fe3884d76c73","fallback":"19"},{"id":"114","name":"POLO R WRC","path":"POLO_R_WRC","filename":"polo_r_wrc","hash":"e5eb6a0e584b8d1b6382c01f0a7aae99","fallback":"1"},{"id":"200","name":"Polski Fiat 126p","path":"126P","filename":"126p","hash":"5635755980590c4466587bf128e1ff02","fallback":"1"},{"id":"208","name":"Porsche 911 Carrera RS 3.0","path":"Porsche_911RS","filename":"Porsche_911RS","hash":"c2a619de940c47cb48ca255b5c2f0336","fallback":"1"},{"id":"243","name":"Porsche 911 GT3 RS (2010) RGT","path":"PORSCHE_GT3_RGT","filename":"PORSCHE_GT3_RGT","hash":"60a5f8d85f0c1ac651bbd8611f2c5659","fallback":"5"},{"id":"209","name":"Porsche 911 SC 3.0 Grp4","path":"Porsche_911SC","filename":"Porsche_911SC","hash":"6662f711364bb7f152de24f2399fbcc6","fallback":"5"},{"id":"141","name":"Porsche 911 SC RS","path":"PORSCHE911_SCRS_GrpB","filename":"PORSCHE911_SCRS_GrpB","hash":"4937ae2fbd384481f5d73b42fbc83720","fallback":"1"},{"id":"185","name":"Porsche 996 GT3","path":"PORSCHE","filename":"PORSCHE","hash":"2dbf6d3aa612761a72646d9826a988ea","fallback":"1"},{"id":"186","name":"Porsche 997 GT3","path":"PORSCHE911GT3RS","filename":"PORSCHE911GT3RS","hash":"d09e1889262b334888edae40bfd6a523","fallback":"1"},{"id":"224","name":"Porsche 997 GT3 2010","path":"PORSCHE911GT3RS_2010","filename":"Porsche_GT3_2010","hash":"cfed6e3deb4f0142ac3372987cc6bcc6","fallback":"5"},{"id":"72","name":"Proton S2000","path":"satria_s2000","filename":"satria_s2000","hash":"fd6886003809cf4c94bca4ae69763d26","fallback":"2"},{"id":"201","name":"Renault 17 Gordini","path":"Renault_17_Gordini","filename":"Renault_17_Gordini","hash":"cc01daf75d8ad13623a2775ef3cdb460","fallback":"1"},{"id":"232","name":"Renault 5 GT Turbo GrpA","path":"5GTT","filename":"5gtt","hash":"5d41828b10b3ff527fcf5a0a6ae03842","fallback":"5"},{"id":"142","name":"Renault 5 Maxi Turbo","path":"R5_Turbo_II","filename":"R5_Turbo_II","hash":"5a36c6cfeec45e3fe7cb15db289b41da","fallback":"1"},{"id":"210","name":"Renault 5 Turbo Cevennes","path":"RENAULT5_Turbo_Grp4","filename":"RENAULT5_Turbo_Grp4","hash":"b10d7e8f2341f9d45f4d738d3849064f","fallback":"1"},{"id":"189","name":"Renault Clio IV R3T","path":"Clio4_R3T","filename":"Clio4_R3T","hash":"5267ef01199512d83ad71344139b77ca","fallback":"4"},{"id":"47","name":"Renault Clio R3","path":"Clio_R3","filename":"Clio_R3","hash":"d18b51660f2afe32575a606a01e75c9a","fallback":"29"},{"id":"254","name":"Renault Clio Rally4","path":"Renault_ClioV_Rally4","filename":"Renault_ClioV_Rally4","hash":"930cacf07dece70da880a1cf5a98129b","fallback":"5"},{"id":"29","name":"Renault Clio S1600","path":"CLIO_S1600","filename":"clio","hash":"4e6ba9e40c2d2ac7734537e1a73fbfff","fallback":"2"},{"id":"88","name":"Renault Clio Williams GrA","path":"RENAULT_CLIO","filename":"Renault_Clio","hash":"92e36a91066a99a505613402d0e6376f","fallback":"1"},{"id":"91","name":"Renault Megane Maxi KitCar","path":"Renault_Megane_Maxi","filename":"Renault_Megane_Maxi","hash":"bcd71e8c62a7018d86138548b43b1db0","fallback":"1"},{"id":"147","name":"Renault Twingo R1","path":"Twingo_R1","filename":"Twingo_R1","hash":"1bfb36c6b86744b0d4c08787b4265e52","fallback":"1"},{"id":"148","name":"Renault Twingo R2 Evo","path":"Twingo_R2","filename":"Twingo_R2","hash":"9d499bcca17fd6796bec3112e1751d82","fallback":"1"},{"id":"94","name":"Seat Cordoba WRC","path":"CORDOBA_E1","filename":"Cordoba_E1","hash":"bd161a835031a9eecc4d039f2d6984a1","fallback":"1"},{"id":"90","name":"Seat Ibiza KitCar Evo2","path":"IBIZA_KC","filename":"Ibiza_KC","hash":"3eea0179b1759097042428ea2a2b7bd2","fallback":"1"},{"id":"242","name":"Seat Leon Cupra R GrpN","path":"leon_cupra_grn","filename":"leon_cupra_grn","hash":"04753f37853091adbbf0af28d800af2a","fallback":"3"},{"id":"95","name":"Skoda 130 RS","path":"Skoda_130RS","filename":"Skoda_130RS","hash":"8bed0c4f7389e3e967061f92051c91a1","fallback":"2"},{"id":"124","name":"Skoda 130LR","path":"skoda_130LR","filename":"skoda_130LR","hash":"f7952049b430ceac6fa38a797866db35","fallback":"5"},{"id":"149","name":"Skoda Fabia R2","path":"Skoda_Fabia_R2","filename":"Skoda_Fabia_R2","hash":"0f8b91d3c4b5d0c06c07f76f173bb35f","fallback":"1"},{"id":"154","name":"Skoda Fabia R5","path":"FABIA_R5","filename":"Fabia_r5","hash":"7791df893fd40466b935bfb67845ee23","fallback":"1"},{"id":"225","name":"Skoda Fabia R5 2018","path":"Fabia_r5_2018","filename":"Fabia_r5_2018","hash":"dbb1587f398875ead0c66dad0bcbbbec","fallback":"5"},{"id":"231","name":"Skoda Fabia R5 evo","path":"Fabia_R5_evo","filename":"Fabia_R5_evo","hash":"a286768967e4d8dbde9eb90bf77912b7","fallback":"5"},{"id":"263","name":"Skoda Fabia RS Rally2","path":"fabia_rs_rally2","filename":"fabia_rs_rally2","hash":"4ca7f3a74c21961368f5e14769f2428b","fallback":"5"},{"id":"26","name":"Skoda Fabia S1600","path":"Fabia_kit_s1600","filename":"fabia_kit_s1600","hash":"7d1cac0b5084585bc25d6cca9eba635c","fallback":"14"},{"id":"53","name":"Skoda Fabia S2000","path":"Fabia_S2000","filename":"fabia2000","hash":"8f52ec483a65de94d9d989410fbccdd7","fallback":"4"},{"id":"74","name":"Skoda Fabia S2000 e2","path":"Fabia_S2000_e2","filename":"Fabia_S2000_e2","hash":"9b85b2c62e7d338b69184559de749d9d","fallback":"53"},{"id":"183","name":"Skoda Fabia S2000 evo2 2012","path":"Fabia_S2000_2012","filename":"Fabia_S2000_2012","hash":"60bb2fbfa971b2b0b1f3610b250b3d4b","fallback":"1"},{"id":"110","name":"Skoda Fabia WRC 2003","path":"FABIA06_2003","filename":"fabia06","hash":"c2632f54220cef856c0f5f3f266ab47a","fallback":"4"},{"id":"14","name":"Skoda Fabia WRC 2005","path":"fabia05","filename":"fabia05","hash":"bab828b8e78835d0146e4c0a9f141a29","fallback":"4"},{"id":"246","name":"Skoda Fabia WRC 2006","path":"FABIA06","filename":"fabia06","hash":"6967913d71d2b1a0b6665813df8986ed","fallback":"5"},{"id":"216","name":"Skoda Favorit 136 L GrpA","path":"Favorit","filename":"Favorit","hash":"634bec0ab57a90966a62de18f19e64a7","fallback":"5"},{"id":"113","name":"Skoda Felicia KitCar","path":"SKODA_felicia_kc","filename":"SKODA_felicia_kc","hash":"d110b9bb07ba0ee0bf8b52531cb386a8","fallback":"2"},{"id":"92","name":"Skoda Octavia KitCar","path":"Octavia_Kitcar","filename":"Octavia_Kitcar","hash":"25da7932d2e2f9520f9fdcae8719fbc2","fallback":"1"},{"id":"43","name":"Skoda Octavia WRC EVO II","path":"Octavia","filename":"Octavia","hash":"d33f4b7c032e9c24ed52fb06b3ca9c71","fallback":"5"},{"id":"55","name":"Subaru Impreza 555","path":"impreza95","filename":"impreza95","hash":"2a69cf4e20f6851b8a9475d20a72b0ef","fallback":"5"},{"id":"193","name":"Subaru Impreza GC8 WRC2000","path":"Impreza00_Maximum","filename":"impreza00","hash":"0265fef77c7a0279b24e491d7a335903","fallback":"7"},{"id":"194","name":"Subaru Impreza GDA WRC2001","path":"Impreza01_AlexRacer","filename":"impreza01","hash":"34edda31c2d202eb7745056d67f2b305","fallback":"5"},{"id":"195","name":"Subaru Impreza GDA WRC2002","path":"Impreza02_AlexRacer","filename":"impreza02","hash":"aa7f2db2f46860f2b262c29d9e90cf84","fallback":"5"},{"id":"24","name":"Subaru Impreza N 2006","path":"IMPREZA06_GrN","filename":"impreza06","hash":"c49d4a8ceb3a40561b1705351f3916bf","fallback":"23"},{"id":"23","name":"Subaru Impreza N11","path":"impreza_n11","filename":"impreza_gpn","hash":"ee2d6b56257108a288365a0553153cfa","fallback":"5"},{"id":"64","name":"Subaru Impreza N14","path":"Impreza_N14","filename":"impreza_N14","hash":"891d8bf361864e672b7e4eef55b1f2b0","fallback":"63"},{"id":"230","name":"Subaru Impreza N14 N15 R4","path":"Impreza_N14_Pro","filename":"impreza_N14","hash":"fb85db475caf0f92b09c4d3154dd0b9e","fallback":"5"},{"id":"109","name":"Subaru Impreza S6 WRC 2000","path":"IMPREZA_2000_maximum","filename":"impreza00","hash":"e6c9af7e3a38a607e525722d48805e6f","fallback":"7"},{"id":"105","name":"Subaru Impreza S9 WRC 2003","path":"impreza_2003_kazhol","filename":"impreza03","hash":"1b5e565cdd51c69126b83ff245c76cb5","fallback":"5"},{"id":"63","name":"Subaru Impreza WRC 08","path":"Subaru_Impreza_s14","filename":"Subaru_Impreza_s14","hash":"34dcafa67c2aad1e15f43dd0c60ef503","fallback":"17"},{"id":"103","name":"Subaru Impreza WRC 2001","path":"IMPREZA01","filename":"impreza01","hash":"7676b2c1edc3dc5cb669b68f86fecfd9","fallback":"7"},{"id":"104","name":"Subaru Impreza WRC 2002","path":"IMPREZA02","filename":"impreza02","hash":"32dfda17e238b6996f48c66900a396b2","fallback":"7"},{"id":"8","name":"Subaru Impreza WRC 2005","path":"IMPREZA05","filename":"impreza05","hash":"fd90251c78d298645cdc6154d230b98e","fallback":"5"},{"id":"9","name":"Subaru Impreza WRC 2006","path":"IMPREZA06","filename":"impreza06","hash":"9f2a046ac3be665ddb09997e2eb7c72f","fallback":"5"},{"id":"61","name":"Subaru Impreza WRC 2008","path":"Impreza08","filename":"impreza08","hash":"0bf169fd2eb08482b2daa3f82bbf5d16","fallback":"17"},{"id":"177","name":"Subaru Legacy RS","path":"Legacy","filename":"Legacy","hash":"0100884151a4e43d1b5aaca53058ef12","fallback":"1"},{"id":"164","name":"Subaru WRX STI NR4 2015","path":"sti_15","filename":"sti_15","hash":"7157de73a5e649ed18487f92ee44b475","fallback":"1"},{"id":"52","name":"Suzuki Ignis S1600","path":"ignis","filename":"Ignis","hash":"51b6eb803efa05ff5940014e987455cf","fallback":"2"},{"id":"31","name":"Suzuki Swift S1600","path":"SWIFT_S1600","filename":"swift_s1600","hash":"7b264fea4188e85c58df25e01974d3b6","fallback":"2"},{"id":"73","name":"Suzuki SX4 WRC","path":"Suzuki_SX4","filename":"Suzuki_SX4","hash":"80bb0980f3b59cdb0dc0d4c548c26663","fallback":"4"},{"id":"202","name":"Talbot Sunbeam Lotus","path":"Talbot_Sunbeam_Lotus","filename":"Talbot_Sunbeam_Lotus","hash":"0c542fa078c80f5a19b884d0abdec5aa","fallback":"1"},{"id":"234","name":"Toyota Celica 2000GT-FOUR RC (ST185) GrpA","path":"CELICA_st185","filename":"CELICA_st185","hash":"869237adccd8b85cac26c6786f57b1d4","fallback":"5"},{"id":"178","name":"Toyota Celica 4WD Turbo ST185","path":"celica93","filename":"celica93","hash":"5ab24d6583db8b2199d22ec3eb7633e1","fallback":"1"},{"id":"179","name":"Toyota Celica GT4 ST165","path":"CELICA_st165","filename":"CELICA_st165","hash":"ae544866db3be35120655669034e81bc","fallback":"1"},{"id":"34","name":"Toyota Celica ST 205","path":"CELICA_st205_v2","filename":"st205","hash":"2a3a306605eb3fe44d91af8d97670ec2","fallback":"6"},{"id":"240","name":"Toyota Celica TCT (TA64) GrpB","path":"TOYOTA_CELICA_TA64_GrpB","filename":"TOYOTA_CELICA_TA64_GrpB","hash":"fee353ebf6f8bedf0335aa53b8fca76f","fallback":"5"},{"id":"108","name":"Toyota Corolla WRC","path":"COROLLA_KUBRT","filename":"corolla","hash":"c04db92a45b9518a671d33e6d65336ad","fallback":"6"},{"id":"180","name":"Toyota Supra MA70 3.0i","path":"Supra_MA70","filename":"Supra_MA70","hash":"8a82364808b03b659671c0e0e4ffe065","fallback":"1"},{"id":"190","name":"Toyota Yaris WRC 2017","path":"YARIS_WRC17","filename":"yaris_wrc","hash":"f4f70550aa102438ec2d3f3587b130c9","fallback":"5"},{"id":"227","name":"Toyota Yaris WRC 2018","path":"YARIS_WRC18","filename":"yaris_wrc","hash":"78b63081684914aae976ffa00f91cf32","fallback":"5"},{"id":"217","name":"Trabant P 800 RS GrpA","path":"Trabant_P800RS","filename":"Trabant_P800RS","hash":"36d7a1d35031636c5a1bcb5f2f8d4393","fallback":"2"},{"id":"87","name":"Vauxhall Astra G KitCar","path":"Astra_Kitcar","filename":"Astra_Kitcar","hash":"2263c1c9e317a67663646bfb803423e4","fallback":"1"},{"id":"89","name":"Volkswagen Golf III KitCar","path":"Golf_III_Kit","filename":"Golf_III_Kit","hash":"d1ad9cee19ff445a598856e783021a47","fallback":"1"},{"id":"49","name":"Volkswagen Golf IV kitcar","path":"GOLF_KC","filename":"golf_kc","hash":"f47ae5392e1948cbbdea2dada6bdc08f","fallback":"0"},{"id":"27","name":"Volkswagen Polo S1600","path":"Polo_s1600","filename":"Polo_s1600","hash":"fd7ad71128ef21b4ca78adbfb650f62a","fallback":"2"},{"id":"45","name":"Volvo 240 Turbo GrpA","path":"Volvo242LE","filename":"Volvo242LE","hash":"68dcabebf256a5d029cb42e69a65f22b","fallback":"3"},{"id":"203","name":"VW 1302 S","path":"Vw_Bettle","filename":"Vw_Bettle","hash":"2e51b284f50762b2bb9c939e671dfff4","fallback":"1"},{"id":"222","name":"VW Golf I GTI GrpA","path":"golf_mk1_g1","filename":"golf_mk1_g1","hash":"da35e692f7497fd75c17572930648057","fallback":"1"},{"id":"223","name":"VW Golf II GTI 16V GrpA","path":"VW_Golf_Mk2","filename":"VW_Golf_Mk2","hash":"d5fe69e01354ab8104093394067d238d","fallback":"1"},{"id":"238","name":"VW Golf II GTI 16V GrpA ngp6","path":"vw_golf_86","filename":"vw_golf_86","hash":"8dbcab327a5890bc8cb71b70e82386ee","fallback":"5"},{"id":"233","name":"VW Polo GTI R5","path":"Polo_gti_r5","filename":"Polo_gti_r5","hash":"3752cc984450b35a364423ef71a82612","fallback":"5"},{"id":"161","name":"VW Polo R WRC 2015","path":"polo_wrc","filename":"polo_wrc","hash":"72647c6edf598b6632351b35adc434b8","fallback":"1"},{"id":"162","name":"VW Polo R WRC 2016","path":"POLO_R_WRC_2016","filename":"polo_wrc_2016","hash":"13f22dfa9002d16d46cc99e8c83c7ddf","fallback":"1"},{"id":"123","name":"Wartburg 353 (beta)","path":"Wartburg_353","filename":"Wartburg_353","hash":"d9dc08b0c71a776bfdc5970fd2d7368e","fallback":"2"},{"id":"50","name":"Zastava Yugo","path":"yugo","filename":"yugo","hash":"87ab97f6dc69c9db71055ef1648c3be2","fallback":"2"}]